LICENSE.txt
README.md
setup.py
analytics_tools/__init__.py
analytics_tools/bivariate_analysis.py
analytics_tools/correlation_heatmap.py
analytics_tools/histogram_distribution.py
analytics_tools/score_analysis.py
analytics_tools/woe_iv.py
analytics_tools.egg-info/PKG-INFO
analytics_tools.egg-info/SOURCES.txt
analytics_tools.egg-info/dependency_links.txt
analytics_tools.egg-info/requires.txt
analytics_tools.egg-info/top_level.txt