Metadata-Version: 2.1
Name: analytics-tools
Version: 0.3.9
Summary: A package to help data analysts at cotidian tasks, mainly EDA and ETL tasks
Author: Arnaldo Joao Bastos Junior
Author-email: arnaldo.jbj@gmail.com
Classifier: Programming Language :: Python :: 3
Classifier: License :: OSI Approved :: MIT License
Classifier: Operating System :: OS Independent
Requires-Python: >=3.6
License-File: LICENSE.txt
